rsutils_django/__init__.py
rsutils_django/settings.py
rsutils_django/urls.py
rsutils_django/wsgi.py
rsutils_django/abstract/__init__.py
rsutils_django/abstract/admin.py
rsutils_django/abstract/apps.py
rsutils_django/abstract/models.py
rsutils_django/abstract/tests.py
rsutils_django/abstract/views.py
rsutils_django/abstract/migrations/__init__.py
rsutils_django/core/__init__.py
rsutils_django/core/admin.py
rsutils_django/core/apps.py
rsutils_django/core/env.py
rsutils_django/core/models.py
rsutils_django/core/tests.py
rsutils_django/core/views.py
rsutils_django/core/migrations/__init__.py
rsutils_django/generic/__init__.py
rsutils_django/generic/admin.py
rsutils_django/generic/apps.py
rsutils_django/generic/models.py
rsutils_django/generic/tests.py
rsutils_django/generic/views.py
rsutils_django/generic/migrations/__init__.py
rsutils_django/tenant/__init__.py
rsutils_django/tenant/admin.py
rsutils_django/tenant/apps.py
rsutils_django/tenant/models.py
rsutils_django/tenant/tests.py
rsutils_django/tenant/views.py
rsutils_django/tenant/migrations/__init__.py
rsutils_django-0.1.4.dist-info/LICENSE
rsutils_django-0.1.4.dist-info/METADATA
rsutils_django-0.1.4.dist-info/WHEEL
rsutils_django-0.1.4.dist-info/top_level.txt
rsutils_django-0.1.4.dist-info/RECORD
